pydevroutes/__init__.py
pydevroutes/add_path.py
pydevroutes/script.py
pydevroutes-0.1.3.dist-info/LICENSE
pydevroutes-0.1.3.dist-info/METADATA
pydevroutes-0.1.3.dist-info/WHEEL
pydevroutes-0.1.3.dist-info/top_level.txt
pydevroutes-0.1.3.dist-info/RECORD
