Metadata-Version: 2.1
Name: pydevroutes
Version: 0.1.3
Summary: A simple package for add dev source paths to sys.path.
Author: Luis Enrique Quispe Paredes (lequispep@gmail.com)
Author-email: lequispep@gmail.com
License: MIT
License-File: LICENSE
